Workbook

Sheet Raw Data
A1: RELIANCE INDUSTRIES LIMITED — RAW DATA (Consolidated, ₹ Crore)
A2: All figures as reported in RIL consolidated financial statements, fiscal year ended 31 March. Source: screener.in (data.sourced from company Annual Reports / BSE filings), stockanalysis.com. Units: ₹ Crore unless noted.
A4: INCOME STATEMENT ITEMS | B4: FY2022 | C4: FY2023 | D4: FY2024 | E4: FY2025 | F4: FY2026 | G4: Source / Note
A5: Revenue from Operations | B5: 694673 | C5: 876396 | D5: 899041 | E5: 962820 | F5: 1055780 | G5: screener.in P&L, 'Sales'
A6: Total Operating Expenses | B6: 586092 | C6: 734078 | D6: 736543 | E6: 797222 | F6: 876715 | G6: screener.in P&L, 'Expenses'
A7: Other Income | B7: 19600 | C7: 12020 | D7: 15792 | E7: 17824 | F7: 28846 | G7: screener.in P&L, 'Other Income'
A8: Depreciation & Amortisation | B8: 29782 | C8: 40303 | D8: 50832 | E8: 53136 | F8: 57688 | G8: screener.in P&L, 'Depreciation'
A9: Finance Costs (Interest) | B9: 14584 | C9: 19571 | D9: 23118 | E9: 24269 | F9: 27061 | G9: screener.in P&L, 'Interest'
A10: Tax Rate (effective, %) | B10: 0.19 | C10: 0.22 | D10: 0.25 | E10: 0.24 | F10: 0.22 | G10: screener.in P&L, 'Tax %'
A11: Profit After Tax (PAT) | B11: 67845 | C11: 74088 | D11: 79020 | E11: 81309 | F11: 95754 | G11: screener.in P&L, 'Net Profit'
A12: EPS (Basic, ₹/share) | B12: 44.87 | C12: 49.29 | D12: 51.45 | E12: 51.47 | F12: 59.69 | G12: screener.in P&L, 'EPS in Rs'
A14: BALANCE SHEET ITEMS | B14: FY2022 | C14: FY2023 | D14: FY2024 | E14: FY2025 | F14: FY2026
A15: Equity Share Capital | B15: 6765 | C15: 6766 | D15: 6766 | E15: 13532 | F15: 13532 | G15: screener.in Balance Sheet / stockanalysis.com
A16: Reserves & Surplus | B16: 772720 | C16: 709106 | D16: 786715 | E16: 829668 | F16: 890498 | G16: screener.in Balance Sheet / stockanalysis.com
A17: Total Borrowings (Debt) | B17: 319158 | C17: 451664 | D17: 350719 | E17: 374313 | F17: 402962 | G17: screener.in Balance Sheet / stockanalysis.com
A18: Other Liabilities (incl. non-current) | B18: 399979 | C18: 438346 | D18: 610848 | E18: 732200 | F18: 870554 | G18: screener.in Balance Sheet / stockanalysis.com
A19: Total Assets / Total Liabilities | B19: 1498622 | C19: 1605882 | D19: 1755048 | E19: 1949713 | F19: 2177546 | G19: screener.in Balance Sheet / stockanalysis.com
A20: Net Fixed Assets (incl. CWIP) | B20: 800304 | C20: 1018557 | D20: 1118840 | E20: 1261751 | F20: 1362481 | G20: screener.in Balance Sheet / stockanalysis.com
A21: Investments | B21: 394264 | C21: 235560 | D21: 225672 | E21: 242381 | F21: 248332 | G21: screener.in Balance Sheet / stockanalysis.com
A22: Other Assets | B22: 304054 | C22: 351765 | D22: 410536 | E22: 445581 | F22: 566733 | G22: screener.in Balance Sheet / stockanalysis.com
A23: Total Current Assets | B23: 347019 | C23: 425296 | D23: 470100 | E23: 499270 | F23: 594249 | G23: screener.in Balance Sheet / stockanalysis.com
A24: Total Current Liabilities | B24: 308662 | C24: 395743 | D24: 397367 | E24: 453737 | F24: 541254 | G24: screener.in Balance Sheet / stockanalysis.com
A26: CASH FLOW ITEMS | B26: FY2022 | C26: FY2023 | D26: FY2024 | E26: FY2025 | F26: FY2026
A27: Cash Flow from Operating Activities | B27: 110654 | C27: 115032 | D27: 158788 | E27: 178703 | F27: 192113 | G27: screener.in Cash Flow statement
A28: Cash Flow from Investing Activities | B28: -109162 | C28: -93001 | D28: -113581 | E28: -137535 | F28: -101089 | G28: screener.in Cash Flow statement
A29: Cash Flow from Financing Activities | B29: 17289 | C29: 10455 | D29: -16646 | E29: -31891 | F29: -51549 | G29: screener.in Cash Flow statement

Sheet Financial Statements
A1: RELIANCE INDUSTRIES LIMITED — FINANCIAL STATEMENTS (Consolidated, ₹ Crore)
A3: INCOME STATEMENT
B4: FY2022 | C4: FY2023 | D4: FY2024 | E4: FY2025 | F4: FY2026
A5: Revenue from Operations | B5: ='Raw Data'!B5 -> 694673 | C5: ='Raw Data'!C5 -> 876396 | D5: ='Raw Data'!D5 -> 899041 | E5: ='Raw Data'!E5 -> 962820 | F5: ='Raw Data'!F5 -> 1055780
A6: Total Operating Expenses | B6: ='Raw Data'!B6 -> 586092 | C6: ='Raw Data'!C6 -> 734078 | D6: ='Raw Data'!D6 -> 736543 | E6: ='Raw Data'!E6 -> 797222 | F6: ='Raw Data'!F6 -> 876715
A7: EBITDA | B7: =B5-B6 -> 108581 | C7: =C5-C6 -> 142318 | D7: =D5-D6 -> 162498 | E7: =E5-E6 -> 165598 | F7: =F5-F6 -> 179065
A8: EBITDA Margin (%) | B8: =B7/B5 -> 0.1563052 | C8: =C7/C5 -> 0.16239006 | D8: =D7/D5 -> 0.18074593 | E8: =E7/E5 -> 0.17199269 | F8: =F7/F5 -> 0.16960446
A9: Depreciation & Amortisation | B9: ='Raw Data'!B8 -> 29782 | C9: ='Raw Data'!C8 -> 40303 | D9: ='Raw Data'!D8 -> 50832 | E9: ='Raw Data'!E8 -> 53136 | F9: ='Raw Data'!F8 -> 57688
A10: EBIT | B10: =B7-B9 -> 78799 | C10: =C7-C9 -> 102015 | D10: =D7-D9 -> 111666 | E10: =E7-E9 -> 112462 | F10: =F7-F9 -> 121377
A11: EBIT Margin (%) | B11: =B10/B5 -> 0.11343323 | C11: =C10/C5 -> 0.11640286 | D11: =D10/D5 -> 0.12420568 | E11: =E10/E5 -> 0.1168048 | F11: =F10/F5 -> 0.11496429
A12: Other Income | B12: ='Raw Data'!B7 -> 19600 | C12: ='Raw Data'!C7 -> 12020 | D12: ='Raw Data'!D7 -> 15792 | E12: ='Raw Data'!E7 -> 17824 | F12: ='Raw Data'!F7 -> 28846
A13: Finance Costs (Interest) | B13: ='Raw Data'!B9 -> 14584 | C13: ='Raw Data'!C9 -> 19571 | D13: ='Raw Data'!D9 -> 23118 | E13: ='Raw Data'!E9 -> 24269 | F13: ='Raw Data'!F9 -> 27061
A14: Profit Before Tax (PBT) | B14: =B10+B12-B13 -> 83815 | C14: =C10+C12-C13 -> 94464 | D14: =D10+D12-D13 -> 104340 | E14: =E10+E12-E13 -> 106017 | F14: =F10+F12-F13 -> 123162
A15: Profit After Tax (PAT) | B15: ='Raw Data'!B11 -> 67845 | C15: ='Raw Data'!C11 -> 74088 | D15: ='Raw Data'!D11 -> 79020 | E15: ='Raw Data'!E11 -> 81309 | F15: ='Raw Data'!F11 -> 95754
A16: Tax Expense (plug: PBT - PAT) | B16: =B14-B15 -> 15970 | C16: =C14-C15 -> 20376 | D16: =D14-D15 -> 25320 | E16: =E14-E15 -> 24708 | F16: =F14-F15 -> 27408
A17: Effective Tax Rate (%) | B17: =B16/B14 -> 0.19053869 | C17: =C16/C14 -> 0.21570122 | D17: =D16/D14 -> 0.2426682 | E17: =E16/E14 -> 0.23305696 | F17: =F16/F14 -> 0.22253617
A18: Net Profit Margin (%) | B18: =B15/B5 -> 0.097664657 | C18: =C15/C5 -> 0.084537127 | D18: =D15/D5 -> 0.087893656 | E18: =E15/E5 -> 0.084448807 | F18: =F15/F5 -> 0.090695031
A19: EPS (Basic, ₹/share) | B19: ='Raw Data'!B12 -> 44.87 | C19: ='Raw Data'!C12 -> 49.29 | D19: ='Raw Data'!D12 -> 51.45 | E19: ='Raw Data'!E12 -> 51.47 | F19: ='Raw Data'!F12 -> 59.69
A21: BALANCE SHEET
A22: Equity Share Capital | B22: ='Raw Data'!B15 -> 6765 | C22: ='Raw Data'!C15 -> 6766 | D22: ='Raw Data'!D15 -> 6766 | E22: ='Raw Data'!E15 -> 13532 | F22: ='Raw Data'!F15 -> 13532
A23: Reserves & Surplus | B23: ='Raw Data'!B16 -> 772720 | C23: ='Raw Data'!C16 -> 709106 | D23: ='Raw Data'!D16 -> 786715 | E23: ='Raw Data'!E16 -> 829668 | F23: ='Raw Data'!F16 -> 890498
A24: Total Shareholders' Equity | B24: =B22+B23 -> 779485 | C24: =C22+C23 -> 715872 | D24: =D22+D23 -> 793481 | E24: =E22+E23 -> 843200 | F24: =F22+F23 -> 904030
A25: Total Borrowings (Debt) | B25: ='Raw Data'!B17 -> 319158 | C25: ='Raw Data'!C17 -> 451664 | D25: ='Raw Data'!D17 -> 350719 | E25: ='Raw Data'!E17 -> 374313 | F25: ='Raw Data'!F17 -> 402962
A26: Other Liabilities | B26: ='Raw Data'!B18 -> 399979 | C26: ='Raw Data'!C18 -> 438346 | D26: ='Raw Data'!D18 -> 610848 | E26: ='Raw Data'!E18 -> 732200 | F26: ='Raw Data'!F18 -> 870554
A27: Total Liabilities (incl. Equity) | B27: =B24+B25+B26 -> 1498622 | C27: =C24+C25+C26 -> 1605882 | D27: =D24+D25+D26 -> 1755048 | E27: =E24+E25+E26 -> 1949713 | F27: =F24+F25+F26 -> 2177546
A28: Net Fixed Assets (incl. CWIP) | B28: ='Raw Data'!B20 -> 800304 | C28: ='Raw Data'!C20 -> 1018557 | D28: ='Raw Data'!D20 -> 1118840 | E28: ='Raw Data'!E20 -> 1261751 | F28: ='Raw Data'!F20 -> 1362481
A29: Investments | B29: ='Raw Data'!B21 -> 394264 | C29: ='Raw Data'!C21 -> 235560 | D29: ='Raw Data'!D21 -> 225672 | E29: ='Raw Data'!E21 -> 242381 | F29: ='Raw Data'!F21 -> 248332
A30: Other Non-Current Assets | B30: ='Raw Data'!B22 -> 304054 | C30: ='Raw Data'!C22 -> 351765 | D30: ='Raw Data'!D22 -> 410536 | E30: ='Raw Data'!E22 -> 445581 | F30: ='Raw Data'!F22 -> 566733
A31: Total Assets | B31: =B28+B29+B30 -> 1498622 | C31: =C28+C29+C30 -> 1605882 | D31: =D28+D29+D30 -> 1755048 | E31: =E28+E29+E30 -> 1949713 | F31: =F28+F29+F30 -> 2177546
A32: memo: Total Current Assets | B32: ='Raw Data'!B23 -> 347019 | C32: ='Raw Data'!C23 -> 425296 | D32: ='Raw Data'!D23 -> 470100 | E32: ='Raw Data'!E23 -> 499270 | F32: ='Raw Data'!F23 -> 594249
A33: memo: Total Current Liabilities | B33: ='Raw Data'!B24 -> 308662 | C33: ='Raw Data'!C24 -> 395743 | D33: ='Raw Data'!D24 -> 397367 | E33: ='Raw Data'!E24 -> 453737 | F33: ='Raw Data'!F24 -> 541254
A35: CASH FLOW STATEMENT
A36: Cash Flow from Operating Activities | B36: ='Raw Data'!B27 -> 110654 | C36: ='Raw Data'!C27 -> 115032 | D36: ='Raw Data'!D27 -> 158788 | E36: ='Raw Data'!E27 -> 178703 | F36: ='Raw Data'!F27 -> 192113
A37: Cash Flow from Investing Activities | B37: ='Raw Data'!B28 -> -109162 | C37: ='Raw Data'!C28 -> -93001 | D37: ='Raw Data'!D28 -> -113581 | E37: ='Raw Data'!E28 -> -137535 | F37: ='Raw Data'!F28 -> -101089
A38: Cash Flow from Financing Activities | B38: ='Raw Data'!B29 -> 17289 | C38: ='Raw Data'!C29 -> 10455 | D38: ='Raw Data'!D29 -> -16646 | E38: ='Raw Data'!E29 -> -31891 | F38: ='Raw Data'!F29 -> -51549
A39: Net Change in Cash | B39: =B36+B37+B38 -> 18781 | C39: =C36+C37+C38 -> 32486 | D39: =D36+D37+D38 -> 28561 | E39: =E36+E37+E38 -> 9277 | F39: =F36+F37+F38 -> 39475
A40: Free Cash Flow (CFO + CFI)* | B40: =B36+B37 -> 1492 | C40: =C36+C37 -> 22031 | D40: =D36+D37 -> 45207 | E40: =E36+E37 -> 41168 | F40: =F36+F37 -> 91024

Sheet Ratio Analysis
A1: RELIANCE INDUSTRIES LIMITED — RATIO ANALYSIS
A3: GROWTH
B4: FY2022 | C4: FY2023 | D4: FY2024 | E4: FY2025 | F4: FY2026
A5: Revenue Growth (YoY %) | B5: n/a | C5: =('Financial Statements'!C5-'Financial Statements'!B5)/'Financial Statements'!B5 -> 0.26159502 | D5: =('Financial Statements'!D5-'Financial Statements'!C5)/'Financial Statements'!C5 -> 0.025838776 | E5: =('Financial Statements'!E5-'Financial Statements'!D5)/'Financial Statements'!D5 -> 0.070941147 | F5: =('Financial Statements'!F5-'Financial Statements'!E5)/'Financial Statements'!E5 -> 0.096549719
A7: PROFITABILITY MARGINS
A8: EBITDA Margin (%) | B8: ='Financial Statements'!B8 -> 0.1563052 | C8: ='Financial Statements'!C8 -> 0.16239006 | D8: ='Financial Statements'!D8 -> 0.18074593 | E8: ='Financial Statements'!E8 -> 0.17199269 | F8: ='Financial Statements'!F8 -> 0.16960446
A9: EBIT Margin (%) | B9: ='Financial Statements'!B11 -> 0.11343323 | C9: ='Financial Statements'!C11 -> 0.11640286 | D9: ='Financial Statements'!D11 -> 0.12420568 | E9: ='Financial Statements'!E11 -> 0.1168048 | F9: ='Financial Statements'!F11 -> 0.11496429
A10: Net Profit Margin (%) | B10: ='Financial Statements'!B18 -> 0.097664657 | C10: ='Financial Statements'!C18 -> 0.084537127 | D10: ='Financial Statements'!D18 -> 0.087893656 | E10: ='Financial Statements'!E18 -> 0.084448807 | F10: ='Financial Statements'!F18 -> 0.090695031
A12: RETURNS
A13: Return on Equity (ROE, %) | B13: ='Financial Statements'!B15/'Financial Statements'!B24 -> 0.087038237 | C13: ='Financial Statements'!C15/'Financial Statements'!C24 -> 0.10349336 | D13: ='Financial Statements'!D15/'Financial Statements'!D24 -> 0.099586506 | E13: ='Financial Statements'!E15/'Financial Statements'!E24 -> 0.09642908 | F13: ='Financial Statements'!F15/'Financial Statements'!F24 -> 0.10591905
A14: Return on Assets (ROA, %) | B14: ='Financial Statements'!B15/'Financial Statements'!B31 -> 0.04527159 | C14: ='Financial Statements'!C15/'Financial Statements'!C31 -> 0.046135395 | D14: ='Financial Statements'!D15/'Financial Statements'!D31 -> 0.04502441 | E14: ='Financial Statements'!E15/'Financial Statements'!E31 -> 0.041703061 | F14: ='Financial Statements'!F15/'Financial Statements'!F31 -> 0.043973353
A16: LIQUIDITY & LEVERAGE
A17: Current Ratio (x) | B17: ='Financial Statements'!B32/'Financial Statements'!B33 -> 1.1242686 | C17: ='Financial Statements'!C32/'Financial Statements'!C33 -> 1.0746773 | D17: ='Financial Statements'!D32/'Financial Statements'!D33 -> 1.1830373 | E17: ='Financial Statements'!E32/'Financial Statements'!E33 -> 1.1003511 | F17: ='Financial Statements'!F32/'Financial Statements'!F33 -> 1.0979115
A18: Debt-to-Equity (x) | B18: ='Financial Statements'!B25/'Financial Statements'!B24 -> 0.40944726 | C18: ='Financial Statements'!C25/'Financial Statements'!C24 -> 0.63092843 | D18: ='Financial Statements'!D25/'Financial Statements'!D24 -> 0.4420005 | E18: ='Financial Statements'!E25/'Financial Statements'!E24 -> 0.44391959 | F18: ='Financial Statements'!F25/'Financial Statements'!F24 -> 0.44573963
A19: Interest Coverage Ratio (x) | B19: ='Financial Statements'!B10/'Financial Statements'!B13 -> 5.403113 | C19: ='Financial Statements'!C10/'Financial Statements'!C13 -> 5.2125594 | D19: ='Financial Statements'!D10/'Financial Statements'!D13 -> 4.8302621 | E19: ='Financial Statements'!E10/'Financial Statements'!E13 -> 4.6339775 | F19: ='Financial Statements'!F10/'Financial Statements'!F13 -> 4.485311
A21: EFFICIENCY
A22: Asset Turnover (x) | B22: ='Financial Statements'!B5/'Financial Statements'!B31 -> 0.46354117 | C22: ='Financial Statements'!C5/'Financial Statements'!C31 -> 0.54574122 | D22: ='Financial Statements'!D5/'Financial Statements'!D31 -> 0.51226006 | E22: ='Financial Statements'!E5/'Financial Statements'!E31 -> 0.49382653 | F22: ='Financial Statements'!F5/'Financial Statements'!F31 -> 0.48484854
A25: 5-Year Revenue CAGR (FY2022–FY2026) | B25: =('Financial Statements'!F5/'Financial Statements'!B5)^(1/4)-1 -> 0.11032023
A26: 5-Year PAT CAGR (FY2022–FY2026) | B26: =('Financial Statements'!F15/'Financial Statements'!B15)^(1/4)-1 -> 0.089958016
A28: Note: ROE and ROA use fiscal year-end (not average) equity/assets. Interest coverage = EBIT / Finance Costs.

Sheet Dashboard
A1: RELIANCE INDUSTRIES LIMITED
A2: Financial Performance Dashboard | FY2022 – FY2026 (Consolidated, ₹ Crore)
B4: Revenue (FY2026) | C4: Revenue CAGR (4-Yr) | D4: EBITDA Margin (FY2026) | E4: ROE (FY2026) | F4: Debt / Equity (FY2026)
B5: ='Financial Statements'!F5/1 -> 1055780 | C5: ='Ratio Analysis'!B25 -> 0.11032023 | D5: ='Financial Statements'!F8 -> 0.16960446 | E5: ='Ratio Analysis'!F13 -> 0.10591905 | F5: ='Ratio Analysis'!F18 -> 0.44573963
B8: FY2022 | C8: FY2023 | D8: FY2024 | E8: FY2025 | F8: FY2026
A9: Revenue (₹ Cr) | B9: ='Financial Statements'!B5 -> 694673 | C9: ='Financial Statements'!C5 -> 876396 | D9: ='Financial Statements'!D5 -> 899041 | E9: ='Financial Statements'!E5 -> 962820 | F9: ='Financial Statements'!F5 -> 1055780
A10: EBITDA (₹ Cr) | B10: ='Financial Statements'!B7 -> 108581 | C10: ='Financial Statements'!C7 -> 142318 | D10: ='Financial Statements'!D7 -> 162498 | E10: ='Financial Statements'!E7 -> 165598 | F10: ='Financial Statements'!F7 -> 179065
A11: PAT (₹ Cr) | B11: ='Financial Statements'!B15 -> 67845 | C11: ='Financial Statements'!C15 -> 74088 | D11: ='Financial Statements'!D15 -> 79020 | E11: ='Financial Statements'!E15 -> 81309 | F11: ='Financial Statements'!F15 -> 95754
A12: EPS (₹) | B12: ='Financial Statements'!B19 -> 44.87 | C12: ='Financial Statements'!C19 -> 49.29 | D12: ='Financial Statements'!D19 -> 51.45 | E12: ='Financial Statements'!E19 -> 51.47 | F12: ='Financial Statements'!F19 -> 59.69
A13: EBITDA Margin (%) | B13: ='Ratio Analysis'!B8 -> 0.1563052 | C13: ='Ratio Analysis'!C8 -> 0.16239006 | D13: ='Ratio Analysis'!D8 -> 0.18074593 | E13: ='Ratio Analysis'!E8 -> 0.17199269 | F13: ='Ratio Analysis'!F8 -> 0.16960446
A14: ROE (%) | B14: ='Ratio Analysis'!B13 -> 0.087038237 | C14: ='Ratio Analysis'!C13 -> 0.10349336 | D14: ='Ratio Analysis'!D13 -> 0.099586506 | E14: ='Ratio Analysis'!E13 -> 0.09642908 | F14: ='Ratio Analysis'!F13 -> 0.10591905
A15: Debt/Equity (x) | B15: ='Ratio Analysis'!B18 -> 0.40944726 | C15: ='Ratio Analysis'!C18 -> 0.63092843 | D15: ='Ratio Analysis'!D18 -> 0.4420005 | E15: ='Ratio Analysis'!E18 -> 0.44391959 | F15: ='Ratio Analysis'!F18 -> 0.44573963
